<?xml version="1.0" encoding="UTF-8"?>
<index_config>
    <national_language>ta</national_language>
    <national_language>ta-IN</national_language>
    <description>
        <p>Tamiḻ index configuration</p>
    </description>
    <collation_spec>
        <java_collation_spec>
            <include_collation_spec>ta-sort-rules.txt</include_collation_spec>
        </java_collation_spec>
    </collation_spec>
    <sort_method>
        <sort_by_members/>
    </sort_method>
    <group_definitions>
        <term_group>
            <group_key>அ</group_key>
            <group_members>
                <char_or_seq>அ</char_or_seq>
                <char_or_seq>ஆ</char_or_seq>
                <char_or_seq>இ</char_or_seq>
                <char_or_seq>ஈ</char_or_seq>
                <char_or_seq>உ</char_or_seq>
                <char_or_seq>ஊ</char_or_seq>
                <char_or_seq>எ</char_or_seq>
                <char_or_seq>ஏ</char_or_seq>
                <char_or_seq>ஐ</char_or_seq>
                <char_or_seq>ஒ</char_or_seq>
                <char_or_seq>ஓ</char_or_seq>
                <char_or_seq>ஔ</char_or_seq>
                <char_or_seq>ஔ</char_or_seq>
            </group_members>
        </term_group>
        <term_group>
            <group_key>க</group_key>
            <group_members>
                <char_or_seq>க</char_or_seq>
            </group_members>
        </term_group>
        <term_group>
            <group_key>ங</group_key>
            <group_members>
                <char_or_seq>ங</char_or_seq>
            </group_members>
        </term_group>
        <term_group>
            <group_key>ச</group_key>
            <group_members>
                <char_or_seq>ச</char_or_seq>
            </group_members>
        </term_group>
        <term_group>
            <group_key>ஞ</group_key>
            <group_members>
                <char_or_seq>ஞ</char_or_seq>
            </group_members>
        </term_group>
        <term_group>
            <group_key>ட</group_key>
            <group_members>
                <char_or_seq>ட</char_or_seq>
            </group_members>
        </term_group>
        <term_group>
            <group_key>ண</group_key>
            <group_members>
                <char_or_seq>ண</char_or_seq>
            </group_members>
        </term_group>
        <term_group>
            <group_key>த</group_key>
            <group_members>
                <char_or_seq>த</char_or_seq>
            </group_members>
        </term_group>
        <term_group>
            <group_key>ந</group_key>
            <group_members>
                <char_or_seq>ந</char_or_seq>
            </group_members>
        </term_group>
        <term_group>
            <group_key>ப</group_key>
            <group_members>
                <char_or_seq>ப</char_or_seq>
            </group_members>
        </term_group>
        <term_group>
            <group_key>ம</group_key>
            <group_members>
                <char_or_seq>ம</char_or_seq>
            </group_members>
        </term_group>
        <term_group>
            <group_key>ய</group_key>
            <group_members>
                <char_or_seq>ய</char_or_seq>
            </group_members>
        </term_group>
        <term_group>
            <group_key>ர</group_key>
            <group_members>
                <char_or_seq>ர</char_or_seq>
            </group_members>
        </term_group>
        <term_group>
            <group_key>ல</group_key>
            <group_members>
                <char_or_seq>ல</char_or_seq>
            </group_members>
        </term_group>
        <term_group>
            <group_key>வ</group_key>
            <group_members>
                <char_or_seq>வ</char_or_seq>
            </group_members>
        </term_group>
        <term_group>
            <group_key>ழ</group_key>
            <group_members>
                <char_or_seq>ழ</char_or_seq>
            </group_members>
        </term_group>
        <term_group>
            <group_key>ள</group_key>
            <group_members>
                <char_or_seq>ள</char_or_seq>
            </group_members>
        </term_group>
        <term_group>
            <group_key>ற</group_key>
            <group_members>
                <char_or_seq>ற</char_or_seq>
            </group_members>
        </term_group>
        <term_group>
            <group_key>ன</group_key>
            <group_members>
                <char_or_seq>ன</char_or_seq>
            </group_members>
        </term_group>
        <term_group>
            <group_key>ஜ</group_key>
            <group_members>
                <char_or_seq>ஜ</char_or_seq>
            </group_members>
        </term_group>
        <term_group>
            <group_key>ஶ</group_key>
            <group_members>
                <char_or_seq>ஶ</char_or_seq>
            </group_members>
        </term_group>
        <term_group>
            <group_key>ஷ</group_key>
            <group_members>
                <char_or_seq>ஷ</char_or_seq>
            </group_members>
        </term_group>
        <term_group>
            <group_key>ஸ</group_key>
            <group_members>
                <char_or_seq>ஸ</char_or_seq>
            </group_members>
        </term_group>
        <term_group>
            <group_key>ஹ</group_key>
            <group_members>
                <char_or_seq>ஹ</char_or_seq>
            </group_members>
        </term_group>
    </group_definitions>
</index_config>